qwhale_client/__init__.py
qwhale_client/client.py
qwhale_client-0.1.20.dist-info/LICENSE
qwhale_client-0.1.20.dist-info/METADATA
qwhale_client-0.1.20.dist-info/WHEEL
qwhale_client-0.1.20.dist-info/top_level.txt
qwhale_client-0.1.20.dist-info/RECORD
