Metadata-Version: 2.1
Name: qwhale-client
Version: 0.1.20
Summary: Python client for Qwhale API
Home-page: https://qwhale.ml
Author: Yehoyada.s
Author-email: hvuhsg6@gmail.com
License: MIT
Download-URL: https://github.com/hvuhsg/qwhale_client/archive/0.1.2.tar.gz
Keywords: API,Client,Qwhale,QWhale,client,storage,MongoDB
Platform: UNKNOWN
Classifier: Development Status :: 3 - Alpha
Classifier: Intended Audience :: Developers
Classifier: Topic :: Software Development :: Build Tools
Classifier: License :: OSI Approved :: MIT License
Classifier: Programming Language :: Python :: 3.6
Classifier: Programming Language :: Python :: 3.7
Classifier: Programming Language :: Python :: 3.8
Requires-Dist: pymongo
Requires-Dist: requests
